<sv:node sv:name="foreignincome" xmlns:sv="http://www.jcp.org/jcr/sv/1.0">
  <sv:property sv:name="jcr:primaryType" sv:type="Name">
    <sv:value>hst:component</sv:value>
  </sv:property>
  <sv:property sv:name="jcr:uuid" sv:type="String">
    <sv:value>44fb5189-9913-45a4-b61a-7a7409099891</sv:value>
  </sv:property>
  <sv:property sv:multiple="true" sv:name="hst:parameternames" sv:type="String">
    <sv:value>bodyCss</sv:value>
  </sv:property>
  <sv:property sv:multiple="true" sv:name="hst:parametervalues" sv:type="String">
    <sv:value>bodyCssClass</sv:value>
  </sv:property>
  <sv:property sv:name="hst:referencecomponent" sv:type="String">
    <sv:value>hst:pages/simplepage.re</sv:value>
  </sv:property>
  <sv:node sv:name="main">
    <sv:property sv:name="jcr:primaryType" sv:type="Name">
      <sv:value>hst:component</sv:value>
    </sv:property>
    <sv:property sv:name="jcr:uuid" sv:type="String">
      <sv:value>45ea85e7-8c07-4d46-ad82-903b8953b308</sv:value>
    </sv:property>
    <sv:property sv:multiple="true" sv:name="hst:parameternames" sv:type="String">
      <sv:value>contentCssClass</sv:value>
    </sv:property>
    <sv:property sv:multiple="true" sv:name="hst:parametervalues" sv:type="String">
      <sv:value>grid-right col-940</sv:value>
    </sv:property>
    <sv:property sv:name="hst:template" sv:type="String">
      <sv:value>standard.main.re</sv:value>
    </sv:property>
    <sv:node sv:name="content">
      <sv:property sv:name="jcr:primaryType" sv:type="Name">
        <sv:value>hst:component</sv:value>
      </sv:property>
      <sv:property sv:name="jcr:uuid" sv:type="String">
        <sv:value>ef32fb0d-a813-45e4-9d5e-a5d77c4ab917</sv:value>
      </sv:property>
      <sv:property sv:name="hst:referencecomponent" sv:type="String">
        <sv:value>hst:components/foreignincome</sv:value>
      </sv:property>
      <sv:node sv:name="foreignincome_add">
        <sv:property sv:name="jcr:primaryType" sv:type="Name">
          <sv:value>hst:component</sv:value>
        </sv:property>
        <sv:property sv:name="jcr:uuid" sv:type="String">
          <sv:value>0d6de4ee-566b-47fb-b069-5e23951eac9d</sv:value>
        </sv:property>
        <sv:property sv:name="hst:componentclassname" sv:type="String">
          <sv:value>com.mootly.wcm.member.ForeignIncome_add</sv:value>
        </sv:property>
        <sv:property sv:multiple="true" sv:name="hst:parameternames" sv:type="String"/>
        <sv:property sv:multiple="true" sv:name="hst:parametervalues" sv:type="String"/>
        <sv:property sv:name="hst:template" sv:type="String">
          <sv:value>foreignincome_add</sv:value>
        </sv:property>
      </sv:node>
    </sv:node>
  </sv:node>
</sv:node>